simuk/__init__.py
simuk/sbc.py
simuk/tests/test_sbc.py
simuk-0.2.0.dist-info/licenses/LICENSE
simuk-0.2.0.dist-info/WHEEL
simuk-0.2.0.dist-info/METADATA
simuk-0.2.0.dist-info/RECORD
