Metadata-Version: 2.4
Name: simuk
Version: 0.2.0
Summary: Simulation based calibration and generation of synthetic data.
Author-email: ArviZ team <arviz.devs@gmail.com>
Requires-Python: >=3.11
Classifier: Development Status :: 3 - Alpha
Classifier: Intended Audience :: Science/Research
Classifier: Intended Audience :: Education
Classifier: License :: OSI Approved :: Apache Software License
Classifier: Operating System :: OS Independent
Classifier: Programming Language :: Python
Classifier: Programming Language :: Python :: 3
Classifier: Programming Language :: Python :: 3.11
Classifier: Programming Language :: Python :: 3.12
License-File: LICENSE
Requires-Dist: arviz_base>=0.5.0
Requires-Dist: tqdm
Project-URL: funding, https://opencollective.com/arviz
Project-URL: source, https://github.com/arviz-devs/simuk
Project-URL: tracker, https://github.com/arviz-devs/simuk/issues
